MANIFEST.in
README.rst
setup.py
collective/.DS_Store
collective/__init__.py
collective/__init__.pyc
collective.ptg.nivoslider.egg-info/PKG-INFO
collective.ptg.nivoslider.egg-info/SOURCES.txt
collective.ptg.nivoslider.egg-info/dependency_links.txt
collective.ptg.nivoslider.egg-info/entry_points.txt
collective.ptg.nivoslider.egg-info/namespace_packages.txt
collective.ptg.nivoslider.egg-info/not-zip-safe
collective.ptg.nivoslider.egg-info/requires.txt
collective.ptg.nivoslider.egg-info/top_level.txt
collective/ptg/.DS_Store
collective/ptg/__init__.py
collective/ptg/__init__.pyc
collective/ptg/nivoslider/.DS_Store
collective/ptg/nivoslider/__init__.py
collective/ptg/nivoslider/__init__.pyc
collective/ptg/nivoslider/configure.zcml
collective/ptg/nivoslider/i18n.sh
collective/ptg/nivoslider/nivoslider.pt
collective/ptg/nivoslider/locales/collective.ptg.nivoslider.pot
collective/ptg/nivoslider/locales/manual.pot
collective/ptg/nivoslider/locales/de/LC_MESSAGES/collective.ptg.nivoslider.mo
collective/ptg/nivoslider/locales/de/LC_MESSAGES/collective.ptg.nivoslider.po
collective/ptg/nivoslider/locales/es/LC_MESSAGES/collective.ptg.nivoslider.mo
collective/ptg/nivoslider/locales/es/LC_MESSAGES/collective.ptg.nivoslider.po
collective/ptg/nivoslider/locales/eu/LC_MESSAGES/collective.ptg.nivoslider.mo
collective/ptg/nivoslider/locales/eu/LC_MESSAGES/collective.ptg.nivoslider.po
collective/ptg/nivoslider/locales/fi/LC_MESSAGES/collective.ptg.nivoslider.mo
collective/ptg/nivoslider/locales/fi/LC_MESSAGES/collective.ptg.nivoslider.po
collective/ptg/nivoslider/locales/fr/LC_MESSAGES/collective.ptg.nivoslider.mo
collective/ptg/nivoslider/locales/fr/LC_MESSAGES/collective.ptg.nivoslider.po
collective/ptg/nivoslider/locales/it/LC_MESSAGES/collective.ptg.nivoslider.mo
collective/ptg/nivoslider/locales/it/LC_MESSAGES/collective.ptg.nivoslider.po
collective/ptg/nivoslider/locales/nl/LC_MESSAGES/collective.ptg.nivoslider.mo
collective/ptg/nivoslider/locales/nl/LC_MESSAGES/collective.ptg.nivoslider.po
collective/ptg/nivoslider/locales/no/LC_MESSAGES/collective.ptg.nivoslider.mo
collective/ptg/nivoslider/locales/no/LC_MESSAGES/collective.ptg.nivoslider.po
collective/ptg/nivoslider/locales/pt_BR/LC_MESSAGES/collective.ptg.nivoslider.mo
collective/ptg/nivoslider/locales/pt_BR/LC_MESSAGES/collective.ptg.nivoslider.po
collective/ptg/nivoslider/resources/.DS_Store
