Metadata-Version: 1.0
Name: collective.ptg.nivoslider
Version: 1.0.6
Summary: Adds Nivoslider to collective.plonetruegallery
Home-page: https://github.com/collective/collective.ptg.nivoslider
Author: Nathan Van Gheem
Author-email: vangheem@gmail.com
License: GPL
Keywords: plone plonetruegallery nivo slider addon
Platform: UNKNOWN
Classifier: Framework :: Plone
Classifier: Programming Language :: Python
